Metadata-Version: 2.1
Name: flexibletitle
Version: 1.0.0
Summary: A flexible smart title case formatter for Python
Author: Khalid Sulaiman Al-Mulaify
Author-email: khalidmfy@gmail.com
Keywords: title case formatter flexible title string manipulation
Classifier: Programming Language :: Python :: 3
Classifier: License :: OSI Approved :: MIT License
Classifier: Operating System :: OS Independent
Requires-Python: >=3.6
License-File: License.txt
